<?xml version="1.0" encoding="utf-8"?>
<Stage xmlns:xsi="http://www.w3.org/2001/XMLSchema-instance" xmlns:xsd="http://www.w3.org/2001/XMLSchema">
  <GameScreenOffset><x>0</x><y>0.0</y><z>0.1</z></GameScreenOffset>
  <Scale>0.0015</Scale>
  <BlockNumX>30</BlockNumX>
  <BlockNumY>30</BlockNumY>
  <BlockMaterials>
    <BlockMaterial>
      <Life>1</Life>
      <Color><r>1</r><g>0</g><b>0</b><a>1</a></Color>
    </BlockMaterial>
    <BlockMaterial>
      <Life>1</Life>
      <Color><r>1</r><g>1</g><b>0</b><a>1</a></Color>
    </BlockMaterial>
    <BlockMaterial>
      <Life>1</Life>
      <Color><r>0</r><g>1</g><b>0</b><a>1</a></Color>
    </BlockMaterial>
    <BlockMaterial>
      <Life>1</Life>
      <Color><r>0</r><g>1</g><b>1</b><a>1</a></Color>
    </BlockMaterial>
    <BlockMaterial>
      <Life>1</Life>
      <Color><r>0</r><g>0</g><b>1</b><a>1</a></Color>
    </BlockMaterial>
    <BlockMaterial>
      <Life>1</Life>
      <Color><r>1</r><g>0</g><b>1</b><a>1</a></Color>
    </BlockMaterial>
    <BlockMaterial>
      <Life>3</Life>
      <Color><r>1</r><g>1</g><b>1</b><a>1</a></Color>
    </BlockMaterial>
  </BlockMaterials>
  <BlockTable>
0,0,0,0,0, 0,0,0,0,0, 0,0,0,0,0, 0,0,0,0,0, 0,0,0,0,0, 0,0,0,0,0,
0,0,0,0,0, 0,0,0,0,0, 0,0,0,0,0, 0,0,0,0,0, 0,0,0,0,0, 0,0,0,0,0,
0,0,0,0,0, 0,0,0,0,0, 0,0,0,0,0, 0,0,0,0,0, 0,0,0,0,0, 0,0,0,0,0,
0,0,0,0,0, 0,0,0,0,0, 0,0,0,0,0, 0,0,0,0,0, 0,0,0,0,0, 0,0,0,0,0,
0,0,0,0,0, 0,0,0,0,0, 0,0,0,0,0, 0,0,0,0,0, 0,0,0,0,0, 0,0,0,0,0,

0,0,0,0,0, 0,0,0,0,0, 0,0,0,0,0, 0,0,0,0,0, 0,0,0,0,0, 0,0,0,0,0,
0,0,0,0,0, 0,0,0,0,0, 0,0,0,0,0, 0,0,0,0,0, 0,0,0,0,0, 0,0,0,0,0,
0,0,0,0,0, 0,0,0,0,0, 0,0,0,0,0, 0,0,0,0,0, 0,0,0,0,0, 0,0,0,0,0,
0,0,0,0,0, 0,0,0,0,0, 0,0,0,0,0, 0,0,0,0,0, 0,0,0,0,0, 0,0,0,0,0,
0,0,0,0,0, 0,0,0,0,0, 0,0,0,0,0, 0,0,0,0,0, 0,0,0,0,0, 0,0,0,0,0,

0,0,0,0,0, 0,0,0,0,0, 0,0,0,0,0, 0,0,0,0,0, 0,0,0,0,0, 0,0,0,0,0,
0,0,0,0,0, 0,0,0,0,0, 0,0,0,0,0, 0,0,0,0,0, 0,0,0,0,0, 0,0,0,0,0,
0,0,0,0,0, 0,0,0,0,0, 0,0,0,0,0, 0,0,0,0,0, 0,0,0,0,0, 0,0,0,0,0,
0,0,0,0,0, 0,0,0,0,0, 0,0,0,0,0, 0,0,0,0,0, 0,0,0,0,0, 0,0,0,0,0,
6,6,6,6,6, 6,6,6,6,6, 0,0,0,0,0, 0,0,0,0,0, 6,6,6,6,6, 6,6,6,6,6,

5,5,5,5,7, 5,5,5,5,5, 0,0,0,0,0, 0,0,0,0,0, 5,5,5,5,5, 7,5,5,5,5,
4,4,4,7,7, 7,4,4,4,4, 0,0,0,0,0, 0,0,0,0,0, 4,4,4,4,7, 7,7,4,4,4,
3,3,3,3,7, 3,3,3,3,3, 0,0,0,0,0, 0,0,0,0,0, 3,3,3,3,3, 7,3,3,3,3,
2,2,2,2,2, 2,2,2,2,2, 0,0,0,0,0, 0,0,0,0,0, 2,2,2,2,2, 2,2,2,2,2,
1,1,1,1,1, 1,1,1,1,1, 0,0,0,0,0, 0,0,0,0,0, 1,1,1,1,1, 1,1,1,1,1,

0,0,0,0,0, 0,0,0,0,0, 0,0,0,0,0, 0,0,0,0,0, 0,0,0,0,0, 0,0,0,0,0,
0,0,0,0,0, 0,0,0,0,0, 0,0,0,0,0, 0,0,0,0,0, 0,0,0,0,0, 0,0,0,0,0,
0,0,0,0,0, 0,0,0,0,0, 0,0,0,0,0, 0,0,0,0,0, 0,0,0,0,0, 0,0,0,0,0,
0,0,0,0,0, 0,0,0,0,0, 0,0,0,0,0, 0,0,0,0,0, 0,0,0,0,0, 0,0,0,0,0,
0,0,0,0,0, 0,0,0,0,0, 0,0,0,0,0, 0,0,0,0,0, 0,0,0,0,0, 0,0,0,0,0,

0,0,0,0,0, 0,0,0,0,0, 0,0,0,0,0, 0,0,0,0,0, 0,0,0,0,0, 0,0,0,0,0,
0,0,0,0,0, 0,0,0,0,0, 0,0,0,0,0, 0,0,0,0,0, 0,0,0,0,0, 0,0,0,0,0,
0,0,0,0,0, 0,0,0,0,0, 0,0,0,0,0, 0,0,0,0,0, 0,0,0,0,0, 0,0,0,0,0,
0,0,0,0,0, 0,0,0,0,0, 0,0,0,0,0, 0,0,0,0,0, 0,0,0,0,0, 0,0,0,0,0,
0,0,0,0,0, 0,0,0,0,0, 0,0,0,0,0, 0,0,0,0,0, 0,0,0,0,0, 0,0,0,0,0,
  </BlockTable>
</Stage>
